{
    "sourceFile": "android/app/src/debug/AndroidManifest.xml",
    "activeCommit": 0,
    "commits": [
        {
            "activePatchIndex": 1,
            "patches": [
                {
                    "date": 1700324418133,
                    "content": "Index: \n===================================================================\n--- \n+++ \n"
                },
                {
                    "date": 1700324448424,
                    "content": "Index: \n===================================================================\n--- \n+++ \n@@ -2,7 +2,6 @@\n     <!-- The INTERNET permission is required for development. Specifically,\r\n          the Flutter tool needs it to communicate with the running application\r\n          to allow setting breakpoints, to provide hot reload, etc.\r\n     -->\r\n-    <uses-permission android:name=\"android.permission.INTERNET\"/><meta-data android:name=\"io.flutter.embedding.android.SplashScreenDrawable\" android:resource=\"@drawable/launch_background\" />\r\n-\r\n+    <uses-permission android:name=\"android.permission.INTERNET\"/>\r\n </manifest>\r\n"
                }
            ],
            "date": 1700324418133,
            "name": "Commit-0",
            "content": "<manifest xmlns:android=\"http://schemas.android.com/apk/res/android\">\r\n    <!-- The INTERNET permission is required for development. Specifically,\r\n         the Flutter tool needs it to communicate with the running application\r\n         to allow setting breakpoints, to provide hot reload, etc.\r\n    -->\r\n    <uses-permission android:name=\"android.permission.INTERNET\"/><meta-data android:name=\"io.flutter.embedding.android.SplashScreenDrawable\" android:resource=\"@drawable/launch_background\" />\r\n\r\n</manifest>\r\n"
        }
    ]
}